hrmcompiler/__init__.py
hrmcompiler/assembler.py
hrmcompiler/conversion.py
hrmcompiler/jsonassembler.py
hrmcompiler/main.py
hrmcompiler/parser.py
hrmcompiler/semantic_check.py
hrmcompiler-0.2.0.dist-info/METADATA
hrmcompiler-0.2.0.dist-info/RECORD
hrmcompiler-0.2.0.dist-info/WHEEL
hrmcompiler-0.2.0.dist-info/entry_points.txt
hrmcompiler-0.2.0.dist-info/top_level.txt
