Metadata-Version: 2.1
Name: hrmcompiler
Version: 0.2.0
Summary: A compiler for a simple language that compiles to Human Resource Machine assembly-like language
Home-page: https://github.com/alfateam123/hrm-compiler
Author: Winter Harrison
Author-email: alfateam123@gmail.com
License: MIT
Keywords: compilers development
Platform: UNKNOWN
Classifier: Development Status :: 5 - Production/Stable
Classifier: Intended Audience :: Developers
Classifier: Topic :: Software Development :: Build Tools
Classifier: License :: OSI Approved :: MIT License
Classifier: Programming Language :: Python :: 3
Classifier: Programming Language :: Python :: 3.3
Classifier: Programming Language :: Python :: 3.4
Classifier: Programming Language :: Python :: 3.5
Classifier: Programming Language :: Python :: 3.6
Classifier: Programming Language :: Python :: 3.7
